ecs_pipeline_deploy/__init__.py
ecs_pipeline_deploy/cli.py
ecs_pipeline_deploy-0.2.0.dist-info/METADATA
ecs_pipeline_deploy-0.2.0.dist-info/RECORD
ecs_pipeline_deploy-0.2.0.dist-info/WHEEL
ecs_pipeline_deploy-0.2.0.dist-info/entry_points.txt
ecs_pipeline_deploy-0.2.0.dist-info/top_level.txt
ecs_pipeline_deploy-0.2.0.dist-info/zip-safe
