Metadata-Version: 2.1
Name: ecs-pipeline-deploy
Version: 0.2.0
Summary: An opinionated deployment application for ECS services
Home-page: UNKNOWN
Author: Gavin M. Roy
Author-email: gavinmroy@gmail.com
License: BSD
Platform: UNKNOWN
Classifier: Development Status :: 3 - Alpha
Classifier: Environment :: Console
Classifier: Environment :: MacOS X
Classifier: Environment :: No Input/Output (Daemon)
Classifier: Intended Audience :: System Administrators
Classifier: License :: OSI Approved :: BSD License
Classifier: Natural Language :: English
Classifier: Operating System :: MacOS
Classifier: Operating System :: POSIX
Classifier: Operating System :: POSIX :: BSD
Classifier: Operating System :: POSIX :: Linux
Classifier: Operating System :: Unix
Classifier: Programming Language :: Python :: 3
Classifier: Programming Language :: Python :: 3.5
Classifier: Programming Language :: Python :: Implementation :: CPython
Classifier: Programming Language :: Python :: Implementation :: PyPy
Requires-Dist: boto3
Requires-Dist: coloredlogs
